development/configuration.py
docs/media/screenshots/compliance-diff.png
docs/media/screenshots/compliance-error.png
docs/media/screenshots/compliance-list.png
docs/media/screenshots/compliance-missing-extra.png
docs/media/screenshots/compliance-ok.png
docs/media/screenshots/compliance-patch.png
docs/media/screenshots/config-temp-substitute.png
docs/media/screenshots/cr-approve-button.png
docs/media/screenshots/cr-approved.png
docs/media/screenshots/cr-collecting-diff-button.png
docs/media/screenshots/cr-completed.png
docs/media/screenshots/cr-created.png
docs/media/screenshots/cr-diffs-tab.png
docs/media/screenshots/cr-job-log.png
docs/media/screenshots/cr-schedule-button.png
docs/media/screenshots/cr-scheduled.png
docs/media/screenshots/cr-unapprove-button.png
docs/media/screenshots/cr-unschedule-button.png
docs/media/screenshots/navbar.png
docs/media/screenshots/platformsetting.png
docs/media/screenshots/render-temp-substitute.png
docs/media/screenshots/script-list.png
docs/media/screenshots/script.png
docs/media/screenshots/substitute.png
netbox_config_diff/__init__.py
netbox_config_diff/choices.py
netbox_config_diff/constants.py
netbox_config_diff/filtersets.py
netbox_config_diff/jobs.py
netbox_config_diff/navigation.py
netbox_config_diff/search.py
netbox_config_diff/tables.py
netbox_config_diff/urls.py
netbox_config_diff/api/__init__.py
netbox_config_diff/api/serializers.py
netbox_config_diff/api/urls.py
netbox_config_diff/api/views.py
netbox_config_diff/compliance/__init__.py
netbox_config_diff/compliance/base.py
netbox_config_diff/compliance/secrets.py
netbox_config_diff/compliance/utils.py
netbox_config_diff/configurator/__init__.py
netbox_config_diff/configurator/base.py
netbox_config_diff/configurator/exceptions.py
netbox_config_diff/configurator/factory.py
netbox_config_diff/configurator/platforms.py
netbox_config_diff/configurator/utils.py
netbox_config_diff/forms/__init__.py
netbox_config_diff/forms/general.py
netbox_config_diff/graphql/__init__.py
netbox_config_diff-2.12.0.dist-info/licenses/LICENSE
netbox_config_diff-2.12.0.dist-info/METADATA
netbox_config_diff-2.12.0.dist-info/WHEEL
netbox_config_diff-2.12.0.dist-info/top_level.txt
netbox_config_diff-2.12.0.dist-info/RECORD
