Metadata-Version: 2.4
Name: netbox-config-diff
Version: 2.12.0
Summary: Push rendered device configurations from NetBox to devices and apply them.
Author: Artem Kotik
Author-email: miaow2@yandex.ru
License:                                  Apache License
Project-URL: repository, https://github.com/miaow2/netbox-config-diff/
Project-URL: homepage, https://miaow2.github.io/netbox-config-diff/
Project-URL: documentation, https://miaow2.github.io/netbox-config-diff/
Keywords: netbox,netbox-plugin,automation,network,network-automation,configuration-compliance
Classifier: Framework :: Django
Classifier: Programming Language :: Python :: 3
Classifier: Programming Language :: Python :: 3 :: Only
Classifier: Programming Language :: Python :: 3.10
Classifier: Programming Language :: Python :: 3.11
Classifier: Programming Language :: Python :: 3.12
Classifier: Topic :: Software Development :: Libraries :: Python Modules
Requires-Python: >=3.10
License-File: LICENSE
Requires-Dist: hier-config==2.3.1
Requires-Dist: netutils==1.12.0
Requires-Dist: scrapli[asyncssh]==2024.07.30
Requires-Dist: scrapli-cfg==2024.07.30
Requires-Dist: scrapli-community==2024.07.30
Provides-Extra: dev
Requires-Dist: ruff==0.9.2; extra == "dev"
Provides-Extra: test
Requires-Dist: factory_boy==3.3.1; extra == "test"
Requires-Dist: pytest==8.3.4; extra == "test"
Requires-Dist: pytest-django==4.9.0; extra == "test"
Dynamic: license-file
